[{"transaction type": "payment", "payee": "Mohamed Mahmoud Ahmed", "amount": "25", "payer": "Moustafa Mahmoud Ahmed"},{"transaction type": "payment", "payee": "Mohamed Mahmoud Ahmed", "amount": "50", "payer": "Moustafa Mahmoud Ahmed"},{"transaction type": "payment", "payee": "Moustafa Mahmoud Ahmed", "amount": "200", "payer": "Mohamed Mahmoud Ahmed"},{"transaction type": "payment", "payee": "Mohamed Mahmoud Ahmed", "amount": "1500", "payer": "Moustafa Mahmoud Ahmed"},{"transaction type": "payment", "payee": "Mohamed Mahmoud Ahmed", "amount": "8000", "payer": "Moustafa Mahmoud Ahmed"}]